applydir-0.3.0.dist-info/METADATA
applydir-0.3.0.dist-info/WHEEL
applydir-0.3.0.dist-info/entry_points.txt
applydir-0.3.0.dist-info/licenses/LICENSE
applydir/__init__.py
applydir/applydir_applicator.py
applydir/applydir_changes.py
applydir/applydir_distance.py
applydir/applydir_error.py
applydir/applydir_file_change.py
applydir/applydir_matcher.py
applydir/config.yaml
applydir/main.py
applydir-0.3.0.dist-info/RECORD
