Metadata-Version: 2.1
Name: applydir
Version: 0.3.0
Summary: Utility to apply changes to files based on AI-generated recommendations.
Keywords: applydir,prepdir,automated code changes,code modification,developer tools,large language models,llm,cli,code automation,ai-driven development,fuzzy matching
Author-Email: eyecantell <paul@pneuma.solutions>
License: MIT
Classifier: Programming Language :: Python :: 3.9
Classifier: Programming Language :: Python :: 3.10
Classifier: Programming Language :: Python :: 3.11
Classifier: Programming Language :: Python :: 3.12
Classifier: Programming Language :: Python :: 3.13
Classifier: License :: OSI Approved :: MIT License
Classifier: Operating System :: OS Independent
Classifier: Environment :: Console
Classifier: Intended Audience :: Developers
Classifier: Topic :: Software Development
Classifier: Topic :: Software Development :: Libraries :: Python Modules
Classifier: Topic :: Utilities
Classifier: Topic :: Text Processing :: Markup
Classifier: Development Status :: 4 - Beta
Project-URL: Repository, https://github.com/eyecantell/applydir
Project-URL: Issues, https://github.com/eyecantell/applydir/issues
Project-URL: Documentation, https://github.com/eyecantell/applydir#readme
Requires-Python: >=3.9
Requires-Dist: typing-extensions>=4.7.1; python_version < "3.11"
Requires-Dist: importlib-resources>=5.0; python_version < "3.9"
Requires-Dist: pyyaml>=6.0
Requires-Dist: dynaconf>=3.2.6
Requires-Dist: prepdir>=0.17.2
Provides-Extra: test
Requires-Dist: pytest>=7.4.4; extra == "test"
Requires-Dist: pytest-cov>=4.1.0; extra == "test"
Requires-Dist: coverage>=7.2.7; extra == "test"
